fuefpyco/__init__.py
fuefpyco/ds.py
fuefpyco/it.py
fuefpyco/pa/__init__.py
fuefpyco/pa/core.py
fuefpyco/pa/process_per_task.py
fuefpyco/pa/process_pool_executor.py
fuefpyco/pd/__init__.py
fuefpyco/pd/generators.py
fuefpyco-0.3.0.dist-info/LICENSE
fuefpyco-0.3.0.dist-info/METADATA
fuefpyco-0.3.0.dist-info/WHEEL
fuefpyco-0.3.0.dist-info/top_level.txt
fuefpyco-0.3.0.dist-info/RECORD
