Metadata-Version: 2.1
Name: fuefpyco
Version: 0.3.0
Summary: Functional Efficient Python Computations
License: " BSD-3-Clause"
Classifier: Programming Language :: Python :: 3
Classifier: Operating System :: OS Independent
Requires-Python: >=3.10
License-File: LICENSE
Requires-Dist: typing-extensions
Provides-Extra: test
Requires-Dist: coverage ; extra == 'test'
Requires-Dist: pytest ; extra == 'test'
